nr_vocabularies_ui/__init__.py
nr_vocabularies_ui/ui_components_specs.py
nr_vocabularies_ui/version.py
nr_vocabularies_ui-1.0.2.dist-info/METADATA
nr_vocabularies_ui-1.0.2.dist-info/WHEEL
nr_vocabularies_ui-1.0.2.dist-info/top_level.txt
nr_vocabularies_ui-1.0.2.dist-info/RECORD
