Metadata-Version: 2.1
Name: nr-vocabularies-ui
Version: 1.0.2
Summary: UI components for nr-vocabularies
Requires-Dist: oarepo-ui
